{
  "projectExportManifest": {
    "exportUploads": false,
    "exportAllInputDatasets": false,
    "exportAllDatasets": false,
    "exportManagedFS": false,
    "exportAnalysisModels": false,
    "exportSavedModels": false,
    "exportModelEvaluationStores": false,
    "exportManagedFolders": false,
    "exportAllInputManagedFolders": false,
    "exportInsightsData": false,
    "includedDatasetsData": [
      {
        "name": "merchant_info",
        "type": "PostgreSQL"
      },
      {
        "name": "cardholder_info",
        "type": "PostgreSQL"
      }
    ],
    "includedSavedModels": [],
    "includedManagedFolders": [],
    "includedModelEvaluationStores": [],
    "exportGitRepository": false
  },
  "instanceFeatures": {
    "showFlowNavLink": false,
    "showLabNavLink": false,
    "showCodeNavLink": false,
    "showSwitchToProjectViewButton": true,
    "showVersionControlFeatures": false
  },
  "useAppHomepage": true,
  "homepageSections": [],
  "label": "app-as-recipe sample",
  "shortDesc": "The template *app-as-recipe sample* was created by Makoto Miyazaki on Nov 24th 2021",
  "tags": [],
  "useAsRecipeSettings": {
    "icon": "icon-dku-application-as-recipe",
    "inputRoles": [
      {
        "objectId": "transactions",
        "roleLabel": "Input",
        "type": "DATASET"
      }
    ],
    "outputRoles": [
      {
        "objectId": "transactions_joined",
        "roleLabel": "Output",
        "type": "DATASET"
      }
    ],
    "variablesEditionTile": {
      "behavior": "MODAL",
      "params": [
        {
          "name": "variable1",
          "type": "STRING",
          "label": "nice label in the form",
          "description": "Help text for the variable",
          "mandatory": false,
          "canSelectForeign": false,
          "markCreatedAsBuilt": false,
          "allowDuplicates": true,
          "getChoicesFromPython": false,
          "disableAutoReload": false,
          "canCreateDataset": false
        },
        {
          "name": "variable2",
          "type": "INT",
          "label": "another label",
          "mandatory": false,
          "canSelectForeign": false,
          "markCreatedAsBuilt": false,
          "allowDuplicates": true,
          "getChoicesFromPython": false,
          "disableAutoReload": false,
          "canCreateDataset": false
        },
        {
          "name": "variable3",
          "type": "SELECT",
          "label": "some selector",
          "mandatory": false,
          "canSelectForeign": false,
          "markCreatedAsBuilt": false,
          "allowDuplicates": true,
          "selectChoices": [
            {
              "value": "val1",
              "label": "First",
              "showInColumnPreview": false,
              "selected": false
            },
            {
              "value": "val2",
              "label": "Second",
              "showInColumnPreview": false,
              "selected": false
            }
          ],
          "getChoicesFromPython": false,
          "disableAutoReload": false,
          "canCreateDataset": false
        }
      ]
    },
    "runScenarioTile": {}
  },
  "instantiationPermission": "EVERYBODY"
}